metloom/__init__.py
metloom/arm_utils.py
metloom/cli.py
metloom/dataframe_utils.py
metloom/request_utils.py
metloom/variables.py
metloom/pointdata/__init__.py
metloom/pointdata/base.py
metloom/pointdata/cdec.py
metloom/pointdata/csas.py
metloom/pointdata/cues.py
metloom/pointdata/files.py
metloom/pointdata/geosphere_austria.py
metloom/pointdata/mesowest.py
metloom/pointdata/norway.py
metloom/pointdata/nws_forecast.py
metloom/pointdata/sail.py
metloom/pointdata/snotel.py
metloom/pointdata/snotel_client.py
metloom/pointdata/snowex.py
metloom/pointdata/usgs.py
metloom-0.8.0.dist-info/licenses/AUTHORS.rst
metloom-0.8.0.dist-info/licenses/LICENSE
metloom-0.8.0.dist-info/METADATA
metloom-0.8.0.dist-info/WHEEL
metloom-0.8.0.dist-info/entry_points.txt
metloom-0.8.0.dist-info/top_level.txt
metloom-0.8.0.dist-info/RECORD
