Metadata-Version: 2.4
Name: metloom
Version: 0.8.0
Summary: Location Oriented Observed Meteorology (LOOM)
Home-page: https://github.com/M3Works/metloom
Author: M3Works
Author-email: m3worksllc@gmail.com
License: BSD license
Keywords: metloom
Classifier: Development Status :: 2 - Pre-Alpha
Classifier: Intended Audience :: Developers
Classifier: License :: OSI Approved :: BSD License
Classifier: Natural Language :: English
Classifier: Programming Language :: Python :: 3
Classifier: Programming Language :: Python :: 3.9
Classifier: Programming Language :: Python :: 3.10
Classifier: Programming Language :: Python :: 3.11
Classifier: Programming Language :: Python :: 3.12
Classifier: Programming Language :: Python :: 3.13
Requires-Python: >=3.7
License-File: LICENSE
License-File: AUTHORS.rst
Requires-Dist: geopandas<2.0.0,>=1.0.0
Requires-Dist: pandas<3.0.0,>2.0.0
Requires-Dist: lxml<6.0.0,>=5.4.0
Requires-Dist: requests<3.0.0,>2.0.0
Requires-Dist: beautifulsoup4<5,>4
Requires-Dist: zeep>4.0.0
Requires-Dist: pydash<9.0.0,>=8.0.0
Dynamic: author
Dynamic: author-email
Dynamic: classifier
Dynamic: description
Dynamic: home-page
Dynamic: keywords
Dynamic: license
Dynamic: license-file
Dynamic: requires-dist
Dynamic: requires-python
Dynamic: summary
